spinthon/__init__.py
spinthon/basis/__init__.py
spinthon/basis/basis.py
spinthon/basis/methyl.py
spinthon/basis/singletTriplet.py
spinthon/basis/vector.py
spinthon/basis/zeeman.py
spinthon/spin/__init__.py
spinthon/spin/geometry.py
spinthon/spin/hamiltonians.py
spinthon/spin/operators.py
spinthon/spin/operatorsOld.py
spinthon/spin/operatorsRotation.py
spinthon/spin/operatorsVeryOld.py
spinthon/spin/system.py
spinthon/spin/single/__init__.py
spinthon/spin/single/operators.py
spinthon-0.21.dist-info/METADATA
spinthon-0.21.dist-info/SOURCES (benno-thinkpad's conflicted copy 2022-05-02).txt
spinthon-0.21.dist-info/WHEEL
spinthon-0.21.dist-info/top_level.txt
spinthon-0.21.dist-info/RECORD
