Metadata-Version: 2.1
Name: spinthon
Version: 0.21
Summary: A python package intended to simulate spin dynamics
Home-page: http://github.com/bennomeier/spinthon
Author: Benno Meier
Author-email: meier.benno@gmail.com
License: MIT
Requires-Dist: numpy
Requires-Dist: scipy
Requires-Dist: spindata
